perceptron_linear_classifier/__init__.py
perceptron_linear_classifier/perceptron.py
perceptron_linear_classifier/tests/__init__.py
perceptron_linear_classifier/tests/test_eval_classifier.py
perceptron_linear_classifier/tests/test_perceptron.py
perceptron_linear_classifier-0.0.2.dist-info/LICENSE
perceptron_linear_classifier-0.0.2.dist-info/METADATA
perceptron_linear_classifier-0.0.2.dist-info/WHEEL
perceptron_linear_classifier-0.0.2.dist-info/top_level.txt
perceptron_linear_classifier-0.0.2.dist-info/RECORD
