Metadata-Version: 2.1
Name: perceptron-linear-classifier
Version: 0.0.2
Summary: A basic Perceptron Linear Classifier algorithm
Author: Prabhav Khera
Author-email: prabhavkhera@hotmail.com
Keywords: python,perceptron,linear classifier,classifier
Classifier: Development Status :: 1 - Planning
Classifier: Intended Audience :: Developers
Classifier: Programming Language :: Python :: 3
Classifier: Operating System :: Unix
Classifier: Operating System :: MacOS :: MacOS X
Classifier: Operating System :: Microsoft :: Windows
License-File: LICENSE
Requires-Dist: numpy
Requires-Dist: matplotlib
